{
  "identify": "KSH-98-附民上-59-20100105-1",
  "court": {
    "name": "臺灣高等法院",
    "code": "KSH"
  },
  "division": {
    "name": "刑事",
    "code": "M"
  },
  "year": 98,
  "word": "附民上",
  "number": "59",
  "jcheck": "1",
  "reason": "損害賠償",
  "content": "臺灣高等法院高雄分院刑事附帶民事訴訟判決\n上  訴  人\n即  原  告  丁○○\n被上  訴人  海閣林休閒渡假酒店股份有限公司\n法定代理人  甲○○\n被上訴人即\n被      告  甲○○\n            未○○\n            巳○○\n            黃○○\n            子○○\n            Ａ○○\n            丙○○\n            戌○○\n            地○○\n            天○○\n            辛○○\n            宙○○\n            丑○○\n            酉○○\n            乙○○\n            午○○\n            宇○○( 原名蔡宜庭)\n            己○○\n            Ｂ○○\n            寅○○\n            卯○○\n            癸○○\n            玄○○\n            戊○○\n            亥○○\n            申○○\n            壬○○\n            辰○○\n            庚○○\n上列當事人間因損害賠償附帶民事訴訟案件，上訴人不服臺灣高\n雄地方法院中華民國98年7 月30日第一審附帶民事訴訟判決（95\n年度附民字第204 號），提起上訴，本院判決如下：\n    主  文\n上訴駁回。\n    事實及理由\n一、上訴人陳述略稱：求為將原判決廢棄，命被上訴人等人應連\n    帶給付上訴人新台幣（下同）54萬元及加計之法定遲延利息\n    ，並援用刑事訴訟之證據。\n    被上訴人等辯稱略以：請求駁回上訴人之上訴。並援用刑事\n    訴訟所為之陳述，即不承認有何常業詐欺之侵權行為。\n二、按刑事訴訟諭知無罪，免訴或不受理之判決者，對於附帶民\n    事訴訟部分應以判決駁回原告之訴，刑事訴訟法第503 條第\n    1 項前段定有明文；又按犯罪而受損害之人，於刑事訴訟程\n    序，得附帶提起民事訴訟，對於被告及依民法負損害賠償責\n    任之人，請求回復其損害，刑事訴訟法第487 條第1 項固定\n    有明文。但附帶民事訴訟之提起，必以刑事訴訟程序之存在\n    為前提，至本條項所定附帶民事訴訟之被告，除刑事被告外\n    ，固兼及於依民法負損害賠償責任之人。惟附帶民事訴訟之\n    原告所主張之共同加害人或依民法應負損害賠償責任之人，\n    必以在刑事訴訟程序中經認定係共同侵權行為之人，或因刑\n    事被告行為，無待於自己為任何行為，即當然負損害賠償責\n    任之人，類如僱用人或法定代理人，始堪以之為刑事附帶民\n    事訴訟事件之被告，否則對之提起附帶民事訴訟，即難謂為\n    合法（最高法院87年度台抗字第278 號、90年度台抗字第54\n    9 號裁定意旨參照）。從而，若原告主張之共同侵權行為人\n    未經刑事訴訟提起公訴或自訴，且其又非因刑事被告行為，\n    無待於自己為任何行為，即當然負損害賠償責任者，對之提\n    起附帶民事訴訟，刑事法院即應以其為不合法，依同法第50\n    2 條第1 項規定為駁回之判決。\n三、經查本院98年度上重訴字第23號被告甲○○、申○○( 原名\n    馮志群) 等人被訴常業詐欺案件，業經本院判決被告等人無\n    罪（臺灣高雄地方法院諭知被告等人均無罪，檢察官不服原\n    判決提起上訴後，亦經本院判決上訴駁回）在案。又該刑事\n    訴訟程序並未認定被上訴人海閣林休閒渡假酒店股份有限公\n    司乃上訴人所受損害之共同侵權行為人，而該公司又非依民\n    法規定，無待自己行為，即應就被上訴人甲○○上開犯罪行\n    為對上訴人所受損害當然負賠償責任之人。原判決依照首開\n    規定，駁回上訴人對於被上訴人等人附帶提起之民事訴訟，\n    經核並無不合，上訴人上訴論旨，求予廢棄改判，均無理由\n    ，應予駁回。\n據上論結，應依刑事訴訟法第490 條前段、第368 條，判決如主\n文。\n中    華    民    國    99    年     1     月    5    日\n                    刑事第三庭  審判長法  官  莊崑山\n                                      法  官  唐照明\n                                      法  官  張意聰\n以上正本證明與原本無異。\n本判決非對於刑事訴訟之判決有上訴時不得上訴。\n如不服本判決應於收受本判決後10日內向本院提出上訴書狀，並\n應敘述具體理由，如未敘述上訴理由者，應於上訴期間屆滿後20\n日內補提理由書狀於本院（均須按他造當事人之人數附繕本）「\n切勿逕送上級法院」。\n中    華    民    國    99    年     1     月    5    日\n                                      書記官  陳金",
  "structure": {
    "main": "上訴駁回。",
    "fact": "一、上訴人陳述略稱：求為將原判決廢棄，命被上訴人等人應連\n    帶給付上訴人新台幣（下同）54萬元及加計之法定遲延利息\n    ，並援用刑事訴訟之證據。\n    被上訴人等辯稱略以：請求駁回上訴人之上訴。並援用刑事\n    訴訟所為之陳述，即不承認有何常業詐欺之侵權行為。\n二、按刑事訴訟諭知無罪，免訴或不受理之判決者，對於附帶民\n    事訴訟部分應以判決駁回原告之訴，刑事訴訟法第503 條第\n    1 項前段定有明文；又按犯罪而受損害之人，於刑事訴訟程\n    序，得附帶提起民事訴訟，對於被告及依民法負損害賠償責\n    任之人，請求回復其損害，刑事訴訟法第487 條第1 項固定\n    有明文。但附帶民事訴訟之提起，必以刑事訴訟程序之存在\n    為前提，至本條項所定附帶民事訴訟之被告，除刑事被告外\n    ，固兼及於依民法負損害賠償責任之人。惟附帶民事訴訟之\n    原告所主張之共同加害人或依民法應負損害賠償責任之人，\n    必以在刑事訴訟程序中經認定係共同侵權行為之人，或因刑\n    事被告行為，無待於自己為任何行為，即當然負損害賠償責\n    任之人，類如僱用人或法定代理人，始堪以之為刑事附帶民\n    事訴訟事件之被告，否則對之提起附帶民事訴訟，即難謂為\n    合法（最高法院87年度台抗字第278 號、90年度台抗字第54\n    9 號裁定意旨參照）。從而，若原告主張之共同侵權行為人\n    未經刑事訴訟提起公訴或自訴，且其又非因刑事被告行為，\n    無待於自己為任何行為，即當然負損害賠償責任者，對之提\n    起附帶民事訴訟，刑事法院即應以其為不合法，依同法第50\n    2 條第1 項規定為駁回之判決。\n三、經查本院98年度上重訴字第23號被告甲○○、申○○( 原名\n    馮志群) 等人被訴常業詐欺案件，業經本院判決被告等人無\n    罪（臺灣高雄地方法院諭知被告等人均無罪，檢察官不服原\n    判決提起上訴後，亦經本院判決上訴駁回）在案。又該刑事\n    訴訟程序並未認定被上訴人海閣林休閒渡假酒店股份有限公\n    司乃上訴人所受損害之共同侵權行為人，而該公司又非依民\n    法規定，無待自己行為，即應就被上訴人甲○○上開犯罪行\n    為對上訴人所受損害當然負賠償責任之人。原判決依照首開\n    規定，駁回上訴人對於被上訴人等人附帶提起之民事訴訟，\n    經核並無不合，上訴人上訴論旨，求予廢棄改判，均無理由\n    ，應予駁回。\n據上論結，應依刑事訴訟法第490 條前段、第368 條，判決如主\n文。",
    "reason": "一、上訴人陳述略稱：求為將原判決廢棄，命被上訴人等人應連\n    帶給付上訴人新台幣（下同）54萬元及加計之法定遲延利息\n    ，並援用刑事訴訟之證據。\n    被上訴人等辯稱略以：請求駁回上訴人之上訴。並援用刑事\n    訴訟所為之陳述，即不承認有何常業詐欺之侵權行為。\n二、按刑事訴訟諭知無罪，免訴或不受理之判決者，對於附帶民\n    事訴訟部分應以判決駁回原告之訴，刑事訴訟法第503 條第\n    1 項前段定有明文；又按犯罪而受損害之人，於刑事訴訟程\n    序，得附帶提起民事訴訟，對於被告及依民法負損害賠償責\n    任之人，請求回復其損害，刑事訴訟法第487 條第1 項固定\n    有明文。但附帶民事訴訟之提起，必以刑事訴訟程序之存在\n    為前提，至本條項所定附帶民事訴訟之被告，除刑事被告外\n    ，固兼及於依民法負損害賠償責任之人。惟附帶民事訴訟之\n    原告所主張之共同加害人或依民法應負損害賠償責任之人，\n    必以在刑事訴訟程序中經認定係共同侵權行為之人，或因刑\n    事被告行為，無待於自己為任何行為，即當然負損害賠償責\n    任之人，類如僱用人或法定代理人，始堪以之為刑事附帶民\n    事訴訟事件之被告，否則對之提起附帶民事訴訟，即難謂為\n    合法（最高法院87年度台抗字第278 號、90年度台抗字第54\n    9 號裁定意旨參照）。從而，若原告主張之共同侵權行為人\n    未經刑事訴訟提起公訴或自訴，且其又非因刑事被告行為，\n    無待於自己為任何行為，即當然負損害賠償責任者，對之提\n    起附帶民事訴訟，刑事法院即應以其為不合法，依同法第50\n    2 條第1 項規定為駁回之判決。\n三、經查本院98年度上重訴字第23號被告甲○○、申○○( 原名\n    馮志群) 等人被訴常業詐欺案件，業經本院判決被告等人無\n    罪（臺灣高雄地方法院諭知被告等人均無罪，檢察官不服原\n    判決提起上訴後，亦經本院判決上訴駁回）在案。又該刑事\n    訴訟程序並未認定被上訴人海閣林休閒渡假酒店股份有限公\n    司乃上訴人所受損害之共同侵權行為人，而該公司又非依民\n    法規定，無待自己行為，即應就被上訴人甲○○上開犯罪行\n    為對上訴人所受損害當然負賠償責任之人。原判決依照首開\n    規定，駁回上訴人對於被上訴人等人附帶提起之民事訴訟，\n    經核並無不合，上訴人上訴論旨，求予廢棄改判，均無理由\n    ，應予駁回。\n據上論結，應依刑事訴訟法第490 條前段、第368 條，判決如主\n文。"
  },
  "characters": {
    "judges": [
      "莊崑山",
      "唐照明",
      "張意聰"
    ],
    "prosecutors": [

    ],
    "lawyers": [

    ],
    "clerks": [

    ],
    "plaintiffs": [
      "丁"
    ],
    "defendants": [
      "甲○○"
    ],
    "prosecutor_office": [

    ],
    "creditors": [

    ],
    "debtors": [

    ],
    "judicial_associate_officer": [

    ]
  },
  "adjudged_at": "2010-01-05",
  "created_at": "2016-01-05 15:09:35",
  "updated_at": "2016-01-05 15:09:35"
}