{
  "identify": "PCD-99-訴-489-20100512-1",
  "court": {
    "name": "臺灣新北地方法院",
    "code": "PCD"
  },
  "division": {
    "name": "民事",
    "code": "V"
  },
  "year": 99,
  "word": "訴",
  "number": "489",
  "jcheck": "1",
  "reason": "返還所有物",
  "content": "臺灣板橋地方法院民事判決               99年度訴字第489號\n原      告  玖益雷射科技股份有限公司\n法定代理人  甲○○\n被      告  乙○○\n上列當事人間請求返還所有物事件，經本院於民國99年4 月26日\n言詞辯論終結，判決如下：\n    主  文\n原告之訴及其假執行之聲請均駁回。\n訴訟費用由原告負擔。\n    事實及理由\n一、原告起訴主張：被告原為原告公司之監察人，於民國98年10\n    月16日以調查公司業務及財務狀況為由藉機取走原告所有之\n    合作金庫銀行二重分行乙存帳號000000000000號自民國93年\n    11月9 日起至98年10月15日之乙存存摺共計22本（下稱系爭\n    存摺），惟被告已取走逾4 個月有餘，其間原告曾函催被告\n    返還，詎被告迄未交還，系爭存摺為原告所有，被告雖有權\n    調閱，但查閱完畢即應歸返，且被告目前已非原告公司之監\n    察人，被告無權占有迄今，爰依民法第767 條規定請求被告\n    返還系爭存摺等語，併為訴之聲明：被告應將原告所有之合\n    作金庫銀行二重分行乙存帳號000000000000 號自93年11月9\n    日起至98年10月15日之乙存存摺共計22本返遷原告。且陳明\n    願供擔保請准宣告假執行。\n二、被告則辯稱：被告為原告公司之監察人，自有權調閱借用系\n    爭存摺，且目前因被告法定代理人涉有背信等罪嫌，由原告\n    向檢察官提起告訴中，系爭存摺係供證據之用，目前仍由原\n    告保管中等語，併為答辯聲明：駁回原告之訴。\n三、經查：\n  (一)按民法第767 條前段規定：「所有人對於無權占有或侵奪其\n    所有物者，得請求返還之。」；又同法第470 條規定：「借\n    用人應於契約所定期限屆滿時，返還借用物；未定期限者，\n    應於依借貸之目的使用完畢時返還之。但經過相當時期，可\n    推定借用人已使用完畢者，貸與人亦得為返還之請求。」、\n    「借貸未定期限，亦不能依借貸之目的而定其期限者，貸與\n    人得隨時請求返還借用物。」、同法第472 條規定：「有左\n    列各款情形之一者，貸與人得終止契約：(一)貸與人因不可預\n    知之情事，自己需用借用物者。(二)借用人違反約定或依物之\n    性質而定之方法使用借用物，或未經貸與人同意允許第三人\n    使用者。(三)因借用人怠於注意，致借用物毀損或有毀損之虞\n    者。(四)借用人死亡者。」，準此以觀，使用借貸如未定期限\n    ，且復未有終止借貸契約時，則出借人得依同法第470條第1\n    項後段或同條第2 項規定請求借貸人返還，惟在出借人未向\n    借用請求返還，且復未終止使用借貸契約時，借用人仍屬有\n    權（基於借用契約關係）占有，是借用人既非屬無權占有，\n    則出借人自無依民法第767 條規定，請求借用人返還借用物\n    之權利至明。\n  (二)系爭存摺為原告公司所有，目前在被告持有中，被告係依公\n    司法規定監察人之查核權，而向原告借用占有系爭存摺，此\n    為兩造所不爭執之事實。原告雖曾函催被告返還，亦有存證\n    信函一件在卷可稽（見本院卷第5、6頁），亦為被告所不爭\n    執，則被告是否有權繼續占有系爭存摺，厥為兩造爭執點。\n  (三)依原告函催被告返還系爭存摺，惟原告並未向被告表示終止\n    使用借貸契約之意思表示，僅表示原告為經營及造冊之所需\n    ，請求被告返還系爭存摺等語，此有存證信函一件在卷可稽\n    （見本院卷第5、6頁），是原告並未向被告表示終止借用契\n    約，且被告係向原告借用系爭存摺而屬有權占有之事實，應\n    可認定。縱令被告符合民法第470條第1 項後段或第2項規定\n    負有返還系爭存摺之義務，但在原告尚未終止兩造間借用契\n    約之前，被告仍屬有權（借用契約關係）占有，僅係被告是\n    否負有依民法第470條第1項或第2 項規定返還之義務。惟原\n    告並未主張依此等請求權請求被告返還系爭存摺，本院自不\n    得為訴外裁判，附此敘明。\n  (四)基上，被告辯稱被告係借用系爭存摺而屬有權占有等語，尚\n    非無據，應可採信。原告主張被告無權占有原告所有之系爭\n    存摺等語，要不可取。從而，原告依民法第767 條前段規定\n    請求被告返還系爭存摺，為無理由，應予駁回。\n四、原告之訴既經駁回，則其假執行聲請，失所附麗，應併予駁\n    回。\n五、本件事證已臻明確，兩造所為其他主張、陳述、證據，經審\n    酌後，均認與本件之結論無礙，爰不再一一論述及調查，併\n    此敘明。\n六、訴訟費用負擔之依據：民事訴訟法第78條。\n中    華    民    國    99    年    5    月    12     日\n                  民事第二庭    法  官  李行一\n以上正本係照原本作成\n如對本判決上訴，須於判決送達後20日內向本院提出上訴狀\n中    華    民    國    99    年    5    月    12     日\n                                書記官  蔡於衡",
  "structure": {
    "main": "原告之訴及其假執行之聲請均駁回。\n訴訟費用由原告負擔。",
    "fact": "一、原告起訴主張：被告原為原告公司之監察人，於民國98年10\n    月16日以調查公司業務及財務狀況為由藉機取走原告所有之\n    合作金庫銀行二重分行乙存帳號000000000000號自民國93年\n    11月9 日起至98年10月15日之乙存存摺共計22本（下稱系爭\n    存摺），惟被告已取走逾4 個月有餘，其間原告曾函催被告\n    返還，詎被告迄未交還，系爭存摺為原告所有，被告雖有權\n    調閱，但查閱完畢即應歸返，且被告目前已非原告公司之監\n    察人，被告無權占有迄今，爰依民法第767 條規定請求被告\n    返還系爭存摺等語，併為訴之聲明：被告應將原告所有之合\n    作金庫銀行二重分行乙存帳號000000000000 號自93年11月9\n    日起至98年10月15日之乙存存摺共計22本返遷原告。且陳明\n    願供擔保請准宣告假執行。\n二、被告則辯稱：被告為原告公司之監察人，自有權調閱借用系\n    爭存摺，且目前因被告法定代理人涉有背信等罪嫌，由原告\n    向檢察官提起告訴中，系爭存摺係供證據之用，目前仍由原\n    告保管中等語，併為答辯聲明：駁回原告之訴。\n三、經查：\n  (一)按民法第767 條前段規定：「所有人對於無權占有或侵奪其\n    所有物者，得請求返還之。」；又同法第470 條規定：「借\n    用人應於契約所定期限屆滿時，返還借用物；未定期限者，\n    應於依借貸之目的使用完畢時返還之。但經過相當時期，可\n    推定借用人已使用完畢者，貸與人亦得為返還之請求。」、\n    「借貸未定期限，亦不能依借貸之目的而定其期限者，貸與\n    人得隨時請求返還借用物。」、同法第472 條規定：「有左\n    列各款情形之一者，貸與人得終止契約：(一)貸與人因不可預\n    知之情事，自己需用借用物者。(二)借用人違反約定或依物之\n    性質而定之方法使用借用物，或未經貸與人同意允許第三人\n    使用者。(三)因借用人怠於注意，致借用物毀損或有毀損之虞\n    者。(四)借用人死亡者。」，準此以觀，使用借貸如未定期限\n    ，且復未有終止借貸契約時，則出借人得依同法第470條第1\n    項後段或同條第2 項規定請求借貸人返還，惟在出借人未向\n    借用請求返還，且復未終止使用借貸契約時，借用人仍屬有\n    權（基於借用契約關係）占有，是借用人既非屬無權占有，\n    則出借人自無依民法第767 條規定，請求借用人返還借用物\n    之權利至明。\n  (二)系爭存摺為原告公司所有，目前在被告持有中，被告係依公\n    司法規定監察人之查核權，而向原告借用占有系爭存摺，此\n    為兩造所不爭執之事實。原告雖曾函催被告返還，亦有存證\n    信函一件在卷可稽（見本院卷第5、6頁），亦為被告所不爭\n    執，則被告是否有權繼續占有系爭存摺，厥為兩造爭執點。\n  (三)依原告函催被告返還系爭存摺，惟原告並未向被告表示終止\n    使用借貸契約之意思表示，僅表示原告為經營及造冊之所需\n    ，請求被告返還系爭存摺等語，此有存證信函一件在卷可稽\n    （見本院卷第5、6頁），是原告並未向被告表示終止借用契\n    約，且被告係向原告借用系爭存摺而屬有權占有之事實，應\n    可認定。縱令被告符合民法第470條第1 項後段或第2項規定\n    負有返還系爭存摺之義務，但在原告尚未終止兩造間借用契\n    約之前，被告仍屬有權（借用契約關係）占有，僅係被告是\n    否負有依民法第470條第1項或第2 項規定返還之義務。惟原\n    告並未主張依此等請求權請求被告返還系爭存摺，本院自不\n    得為訴外裁判，附此敘明。\n  (四)基上，被告辯稱被告係借用系爭存摺而屬有權占有等語，尚\n    非無據，應可採信。原告主張被告無權占有原告所有之系爭\n    存摺等語，要不可取。從而，原告依民法第767 條前段規定\n    請求被告返還系爭存摺，為無理由，應予駁回。\n四、原告之訴既經駁回，則其假執行聲請，失所附麗，應併予駁\n    回。\n五、本件事證已臻明確，兩造所為其他主張、陳述、證據，經審\n    酌後，均認與本件之結論無礙，爰不再一一論述及調查，併\n    此敘明。\n六、訴訟費用負擔之依據：民事訴訟法第78條。",
    "reason": "一、原告起訴主張：被告原為原告公司之監察人，於民國98年10\n    月16日以調查公司業務及財務狀況為由藉機取走原告所有之\n    合作金庫銀行二重分行乙存帳號000000000000號自民國93年\n    11月9 日起至98年10月15日之乙存存摺共計22本（下稱系爭\n    存摺），惟被告已取走逾4 個月有餘，其間原告曾函催被告\n    返還，詎被告迄未交還，系爭存摺為原告所有，被告雖有權\n    調閱，但查閱完畢即應歸返，且被告目前已非原告公司之監\n    察人，被告無權占有迄今，爰依民法第767 條規定請求被告\n    返還系爭存摺等語，併為訴之聲明：被告應將原告所有之合\n    作金庫銀行二重分行乙存帳號000000000000 號自93年11月9\n    日起至98年10月15日之乙存存摺共計22本返遷原告。且陳明\n    願供擔保請准宣告假執行。\n二、被告則辯稱：被告為原告公司之監察人，自有權調閱借用系\n    爭存摺，且目前因被告法定代理人涉有背信等罪嫌，由原告\n    向檢察官提起告訴中，系爭存摺係供證據之用，目前仍由原\n    告保管中等語，併為答辯聲明：駁回原告之訴。\n三、經查：\n  (一)按民法第767 條前段規定：「所有人對於無權占有或侵奪其\n    所有物者，得請求返還之。」；又同法第470 條規定：「借\n    用人應於契約所定期限屆滿時，返還借用物；未定期限者，\n    應於依借貸之目的使用完畢時返還之。但經過相當時期，可\n    推定借用人已使用完畢者，貸與人亦得為返還之請求。」、\n    「借貸未定期限，亦不能依借貸之目的而定其期限者，貸與\n    人得隨時請求返還借用物。」、同法第472 條規定：「有左\n    列各款情形之一者，貸與人得終止契約：(一)貸與人因不可預\n    知之情事，自己需用借用物者。(二)借用人違反約定或依物之\n    性質而定之方法使用借用物，或未經貸與人同意允許第三人\n    使用者。(三)因借用人怠於注意，致借用物毀損或有毀損之虞\n    者。(四)借用人死亡者。」，準此以觀，使用借貸如未定期限\n    ，且復未有終止借貸契約時，則出借人得依同法第470條第1\n    項後段或同條第2 項規定請求借貸人返還，惟在出借人未向\n    借用請求返還，且復未終止使用借貸契約時，借用人仍屬有\n    權（基於借用契約關係）占有，是借用人既非屬無權占有，\n    則出借人自無依民法第767 條規定，請求借用人返還借用物\n    之權利至明。\n  (二)系爭存摺為原告公司所有，目前在被告持有中，被告係依公\n    司法規定監察人之查核權，而向原告借用占有系爭存摺，此\n    為兩造所不爭執之事實。原告雖曾函催被告返還，亦有存證\n    信函一件在卷可稽（見本院卷第5、6頁），亦為被告所不爭\n    執，則被告是否有權繼續占有系爭存摺，厥為兩造爭執點。\n  (三)依原告函催被告返還系爭存摺，惟原告並未向被告表示終止\n    使用借貸契約之意思表示，僅表示原告為經營及造冊之所需\n    ，請求被告返還系爭存摺等語，此有存證信函一件在卷可稽\n    （見本院卷第5、6頁），是原告並未向被告表示終止借用契\n    約，且被告係向原告借用系爭存摺而屬有權占有之事實，應\n    可認定。縱令被告符合民法第470條第1 項後段或第2項規定\n    負有返還系爭存摺之義務，但在原告尚未終止兩造間借用契\n    約之前，被告仍屬有權（借用契約關係）占有，僅係被告是\n    否負有依民法第470條第1項或第2 項規定返還之義務。惟原\n    告並未主張依此等請求權請求被告返還系爭存摺，本院自不\n    得為訴外裁判，附此敘明。\n  (四)基上，被告辯稱被告係借用系爭存摺而屬有權占有等語，尚\n    非無據，應可採信。原告主張被告無權占有原告所有之系爭\n    存摺等語，要不可取。從而，原告依民法第767 條前段規定\n    請求被告返還系爭存摺，為無理由，應予駁回。\n四、原告之訴既經駁回，則其假執行聲請，失所附麗，應併予駁\n    回。\n五、本件事證已臻明確，兩造所為其他主張、陳述、證據，經審\n    酌後，均認與本件之結論無礙，爰不再一一論述及調查，併\n    此敘明。\n六、訴訟費用負擔之依據：民事訴訟法第78條。"
  },
  "characters": {
    "judges": [
      "李行一"
    ],
    "prosecutors": [

    ],
    "lawyers": [

    ],
    "clerks": [

    ],
    "plaintiffs": [
      "玖益雷射科技股份有限公司"
    ],
    "defendants": [
      "乙○○"
    ],
    "prosecutor_office": [

    ],
    "creditors": [

    ],
    "debtors": [

    ],
    "judicial_associate_officer": [

    ]
  },
  "adjudged_at": "2010-05-12",
  "created_at": "2016-01-05 12:28:34",
  "updated_at": "2016-01-05 12:28:34"
}