{
  "identify": "TYD-99-司票-2280-20100512-1",
  "court": {
    "name": "臺灣桃園地方法院",
    "code": "TYD"
  },
  "division": {
    "name": "民事",
    "code": "V"
  },
  "year": 99,
  "word": "司票",
  "number": "2280",
  "jcheck": "1",
  "reason": "本票裁定",
  "content": "臺灣桃園地方法院簡易庭民事裁定      99年度司票字第2280號\n聲  請  人  乙○○\n上列聲請人與相對人甲○○間請求本票裁定事件，聲請人應於收\n受本裁定之日起5 日內，補正下列事項，逾期即駁回其聲請，特\n此裁定。\n壹、應補正之事項：表明提示日及正確利息起算日（本票未載到\n    期日者，應自提示日起算利息）。。\n貳、本裁定不得抗告。\n中    華    民    國    99    年    5     月    12    日\n                  簡易庭司法事務官",
  "structure": {
  },
  "characters": {
    "judges": [

    ],
    "prosecutors": [

    ],
    "lawyers": [

    ],
    "clerks": [

    ],
    "plaintiffs": [

    ],
    "defendants": [

    ],
    "prosecutor_office": [
      "乙"
    ],
    "creditors": [

    ],
    "debtors": [

    ],
    "judicial_associate_officer": [

    ]
  },
  "adjudged_at": "2010-05-12",
  "created_at": "2016-01-05 12:41:13",
  "updated_at": "2016-01-05 12:41:13"
}